django_security_patch/__init__.py
django_security_patch/middleware.py
django_security_patch/settings.py
django_security_patch-0.0.3.dist-info/LICENSE
django_security_patch-0.0.3.dist-info/METADATA
django_security_patch-0.0.3.dist-info/WHEEL
django_security_patch-0.0.3.dist-info/top_level.txt
django_security_patch-0.0.3.dist-info/RECORD
