Metadata-Version: 2.1
Name: django-security-patch
Version: 0.0.3
Summary: Includes some security patches for better security in Django applications.
Home-page: https://github.com/Execut3/django-security-patch
Author: Reza Torkaman Ahmadi
Author-email: execut3.binarycodes@gmail.com
License: GPT
Keywords: django,security
Platform: UNKNOWN
Classifier: Framework :: Django
